{
  "date": "7 Jul 2026, 09:28 UTC",
  "generated_at": "2026-07-07T09:28:11.089Z",
  "source": "https://theanalyst.com/competition/fifa-world-cup/predictions",
  "teams": {
    "France": {
      "L16": 100,
      "QF": 100,
      "SF": 72.14,
      "FIN": 42.9,
      "CH": 27.91
    },
    "Spain": {
      "L16": 100,
      "QF": 100,
      "SF": 69.51,
      "FIN": 36.88,
      "CH": 22.73
    },
    "England": {
      "L16": 100,
      "QF": 100,
      "SF": 62.16,
      "FIN": 37.19,
      "CH": 17.23
    },
    "Argentina": {
      "L16": 100,
      "QF": 80.58,
      "SF": 51.57,
      "FIN": 26.6,
      "CH": 11.73
    },
    "Norway": {
      "L16": 100,
      "QF": 100,
      "SF": 37.84,
      "FIN": 19.06,
      "CH": 7.2
    },
    "Morocco": {
      "L16": 100,
      "QF": 100,
      "SF": 27.86,
      "FIN": 10.37,
      "CH": 4.26
    },
    "Belgium": {
      "L16": 100,
      "QF": 100,
      "SF": 30.49,
      "FIN": 9.85,
      "CH": 3.87
    },
    "Colombia": {
      "L16": 100,
      "QF": 57.12,
      "SF": 24.2,
      "FIN": 9.22,
      "CH": 2.85
    },
    "Switzerland": {
      "L16": 100,
      "QF": 42.88,
      "SF": 17.62,
      "FIN": 6.44,
      "CH": 1.98
    },
    "Egypt": {
      "L16": 100,
      "QF": 19.42,
      "SF": 6.62,
      "FIN": 1.5,
      "CH": 0.25
    },
    "Mexico": {
      "L16": 100,
      "QF": 0,
      "SF": 0,
      "FIN": 0,
      "CH": 0
    },
    "South Africa": {
      "L16": 0,
      "QF": 0,
      "SF": 0,
      "FIN": 0,
      "CH": 0
    },
    "Canada": {
      "L16": 0,
      "QF": 0,
      "SF": 0,
      "FIN": 0,
      "CH": 0
    },
    "Brazil": {
      "L16": 100,
      "QF": 0,
      "SF": 0,
      "FIN": 0,
      "CH": 0
    },
    "Scotland": {
      "L16": 0,
      "QF": 0,
      "SF": 0,
      "FIN": 0,
      "CH": 0
    },
    "USA": {
      "L16": 100,
      "QF": 0,
      "SF": 0,
      "FIN": 0,
      "CH": 0
    },
    "Australia": {
      "L16": 0,
      "QF": 0,
      "SF": 0,
      "FIN": 0,
      "CH": 0
    },
    "Paraguay": {
      "L16": 0,
      "QF": 0,
      "SF": 0,
      "FIN": 0,
      "CH": 0
    },
    "Germany": {
      "L16": 0,
      "QF": 0,
      "SF": 0,
      "FIN": 0,
      "CH": 0
    },
    "Ivory Coast": {
      "L16": 0,
      "QF": 0,
      "SF": 0,
      "FIN": 0,
      "CH": 0
    },
    "Ecuador": {
      "L16": 0,
      "QF": 0,
      "SF": 0,
      "FIN": 0,
      "CH": 0
    },
    "Netherlands": {
      "L16": 0,
      "QF": 0,
      "SF": 0,
      "FIN": 0,
      "CH": 0
    },
    "Japan": {
      "L16": 0,
      "QF": 0,
      "SF": 0,
      "FIN": 0,
      "CH": 0
    },
    "Sweden": {
      "L16": 0,
      "QF": 0,
      "SF": 0,
      "FIN": 0,
      "CH": 0
    },
    "Uruguay": {
      "L16": 0,
      "QF": 0,
      "SF": 0,
      "FIN": 0,
      "CH": 0
    },
    "Senegal": {
      "L16": 0,
      "QF": 0,
      "SF": 0,
      "FIN": 0,
      "CH": 0
    },
    "Austria": {
      "L16": 0,
      "QF": 0,
      "SF": 0,
      "FIN": 0,
      "CH": 0
    },
    "Algeria": {
      "L16": 0,
      "QF": 0,
      "SF": 0,
      "FIN": 0,
      "CH": 0
    },
    "Portugal": {
      "L16": 0,
      "QF": 0,
      "SF": 0,
      "FIN": 0,
      "CH": 0
    },
    "Uzbekistan": {
      "L16": 0,
      "QF": 0,
      "SF": 0,
      "FIN": 0,
      "CH": 0
    },
    "Croatia": {
      "L16": 0,
      "QF": 0,
      "SF": 0,
      "FIN": 0,
      "CH": 0
    },
    "Ghana": {
      "L16": 0,
      "QF": 0,
      "SF": 0,
      "FIN": 0,
      "CH": 0
    }
  }
}
